자바에 대한 기본기가 부족하다 느껴 자바의 정석 공부 도중, 클래스 메서드와 인스턴스 메서드에 대해 읽다 다음의 문구를 읽고 문득 실제 어떤 차이가 있는지 궁금해졌다. 

```
메서드의 작업 내용중에서 인스턴스 변수를 필요로 한다면 static을 붙일 수 없다. 반대로 인스턴스 변수를 필요로 하지 않는다면 
static 변수를 붙이자. 메소드 호출시간이 짧아지므로 성능이 향상된다. static을 안 붙인 메서드는 실행시 호출되어야 할 메서드를 찾는 과정이
추가적으로 필요하기 때문에 시간이 더 걸린다. 
```


---
다음의 테스트 클래스를 생성하여 바이트 코드를 확인해보았다. 

```java
public class Test {
    private int test;
    private static int test2;

    void method() {}
    static void method2() {}

    public static void main(String[] args) {
        Test instance1 = new Test();
        Test instance2 = new Test();

        instance1.method();
        instance2.method();

        instance1.method2();
        instance2.method2();
    }
}
```

---

```
Classfile /Users/gimhanseong/Downloads/test/src/Test.class
  Last modified 2022. 8. 22.; size 468 bytes
  MD5 checksum ad756b11b9b21619aa7e804b9101dbcc
  Compiled from "Test.java"
public class Test
  minor version: 0
  major version: 55
  flags: (0x0021) ACC_PUBLIC, ACC_SUPER
  this_class: #2                          // Test
  super_class: #6                         // java/lang/Object
  interfaces: 0, fields: 2, methods: 4, attributes: 1
Constant pool:
   #1 = Methodref          #6.#20         // java/lang/Object."<init>":()V
   #2 = Class              #21            // Test
   #3 = Methodref          #2.#20         // Test."<init>":()V
   #4 = Methodref          #2.#22         // Test.method:()V
   #5 = Methodref          #2.#23         // Test.method2:()V
   #6 = Class              #24            // java/lang/Object
   #7 = Utf8               test
   #8 = Utf8               I
   #9 = Utf8               test2
  #10 = Utf8               <init>
  #11 = Utf8               ()V
  #12 = Utf8               Code
  #13 = Utf8               LineNumberTable
  #14 = Utf8               method
  #15 = Utf8               method2
  #16 = Utf8               main
  #17 = Utf8               ([Ljava/lang/String;)V
  #18 = Utf8               SourceFile
  #19 = Utf8               Test.java
  #20 = NameAndType        #10:#11        // "<init>":()V
  #21 = Utf8               Test
  #22 = NameAndType        #14:#11        // method:()V
  #23 = NameAndType        #15:#11        // method2:()V
  #24 = Utf8               java/lang/Object
{
  private int test;
    descriptor: I
    flags: (0x0002) ACC_PRIVATE

  private static int test2;
    descriptor: I
    flags: (0x000a) ACC_PRIVATE, ACC_STATIC

  public Test();
    descriptor: ()V
    flags: (0x0001) ACC_PUBLIC
    Code:
      stack=1, locals=1, args_size=1
         0: aload_0
         1: invokespecial #1                  // Method java/lang/Object."<init>":()V
         4: return
      LineNumberTable:
        line 1: 0

  void method();
    descriptor: ()V
    flags: (0x0000)
    Code:
      stack=0, locals=1, args_size=1
         0: return
      LineNumberTable:
        line 5: 0

  static void method2();
    descriptor: ()V
    flags: (0x0008) ACC_STATIC
    Code:
      stack=0, locals=0, args_size=0
         0: return
      LineNumberTable:
        line 6: 0

  public static void main(java.lang.String[]);
    descriptor: ([Ljava/lang/String;)V
    flags: (0x0009) ACC_PUBLIC, ACC_STATIC
    Code:
      stack=2, locals=3, args_size=1
         0: new           #2                  // class Test
         3: dup
         4: invokespecial #3                  // Method "<init>":()V
         7: astore_1
         8: new           #2                  // class Test
        11: dup
        12: invokespecial #3                  // Method "<init>":()V
        15: astore_2
        16: aload_1
        17: invokevirtual #4                  // Method method:()V
        20: aload_2
        21: invokevirtual #4                  // Method method:()V
        24: aload_1
        25: pop
        26: invokestatic  #5                  // Method method2:()V
        29: aload_2
        30: pop
        31: invokestatic  #5                  // Method method2:()V
        34: return
      LineNumberTable:
        line 9: 0
        line 10: 8
        line 12: 16
        line 13: 20
        line 15: 24
        line 16: 29
        line 17: 34
}
SourceFile: "Test.java"
```

오브젝트 코드 관련해서 읽으면서 좀 찾아본 내용들 

major version: 55   // java 1.1 부터 45 으로 나타낸다. 55는 java 11로 컴파일된 클래스 파일라는 정보를 알려준다.

Constant pool : 클래스의 코드를 동작시키기 위한 상수들을 모아놓은 것

Constant pool은 코드에서 사용된 리터럴들과 컴파일러에 의해 생성된 symbolic references들을 모두 포함한다.

symbolic references: 코드에 의해 참조되는 클래스명, 메서드명, 필드명이 포함된다. jvm은 이를 통해 각기 다른 클래스간의 link를 생성한다. 


---
바이트 코드 상에서 결국 invokevirtual   vs  invokestatic 두 가지 instruction만 다르고 상수풀을 참조하고 있는 부분은 같다. 

그렇다면 두 명령어는 무슨 차이가 있을까? 

##### invokevirtual


#### invokestatic

```
invokestatic indexbyte1 indexbyte2  

indexbyte1 indexbyte2 : 호출하고자하는 클래스 함수가 현재 클래스의 상수풀에서 몇 번째 엔트리에 존재하는 지를 나타낸다. (총 2바이트이며 2^16개의 엔트리를 참조할 수 있다.)

즉 참조되는 상수풀은 (indexbyte1 << 8) | indexbyte2) 가 된다.


```

참고 : [Jvm_Instructions](https://docs.oracle.com/javase/specs/jvms/se7/html/jvms-6.html#jvms-6.5.invokevirtual)

---
### javap 사용 방법

**javap : 하나 이상의 class 파일을 역어셈블한다.**

여러 옵션들 

 -v  -verbose : Print additional information (여러 추가적인 정보들을 출력한다)
 
 -s : Print internal type signatures
 
 ---
 클래스 멤버 또는 메서드에 대한 접근 제어자에 따른 옵션 
 
 ```
 -private : Show all classes and members  (-p와 -private은 동일하다)
 -public : Show only public classes and members
 -protected :  Show protected/public classes and members
 -package :   Show package/protected/public classes and members (default)
 ```

javap -v -p -s 클래스명.class > 원하는파일명.txt

를 통해 역어셈블된 자바 바이트 코드를 확인해서 분석할 수 있다. 

---
### REFERENCE 
[REF 1](https://iamsang.com/blog/2012/08/19/introduction-to-java-bytecode/)

[REF 2](https://tlo-developer.tistory.com/262)

[REF 3](https://wonit.tistory.com/589)

[REF 4](https://stackoverflow.com/questions/10209952/what-is-the-purpose-of-the-java-constant-pool)


[Naver D2: JVM Internal](https://d2.naver.com/helloworld/1230)
