자바에 대한 기본기가 부족하다 느껴 자바의 정석 공부 도중, 클래스 메서드와 인스턴스 메서드에 대해 읽다 다음의 문구를 읽고 문득 실제 어떤 차이가 있는지 궁금해졌다. 

```
메서드의 작업 내용중에서 인스턴스 변수를 필요로 한다면 static을 붙일 수 없다. 반대로 인스턴스 변수를 필요로 하지 않는다면 
static 변수를 붙이자. 메소드 호출시간이 짧아지므로 성능이 향상된다. static을 안 붙인 메서드는 실행시 호출되어야 할 메서드를 찾는 과정이
추가적으로 필요하기 때문에 시간이 더 걸린다. 
```


---
다음의 테스트 클래스를 생성하여 바이트 코드를 확인해보았다. 

```java
public class Test {
    private int test;
    private static int test2;

    void method() {}
    static void method2() {}

    public static void main(String[] args) {
        Test instance1 = new Test();
        Test instance2 = new Test();

        instance1.method();
        instance2.method();

        instance1.method2();
        instance2.method2();
    }
}
```

---

```
Classfile /Users/gimhanseong/Downloads/test/src/Test.class
  Last modified 2022. 8. 22.; size 468 bytes
  MD5 checksum ad756b11b9b21619aa7e804b9101dbcc
  Compiled from "Test.java"
public class Test
  minor version: 0
  major version: 55
  flags: (0x0021) ACC_PUBLIC, ACC_SUPER
  this_class: #2                          // Test
  super_class: #6                         // java/lang/Object
  interfaces: 0, fields: 2, methods: 4, attributes: 1
Constant pool:
   #1 = Methodref          #6.#20         // java/lang/Object."<init>":()V
   #2 = Class              #21            // Test
   #3 = Methodref          #2.#20         // Test."<init>":()V
   #4 = Methodref          #2.#22         // Test.method:()V
   #5 = Methodref          #2.#23         // Test.method2:()V
   #6 = Class              #24            // java/lang/Object
   #7 = Utf8               test
   #8 = Utf8               I
   #9 = Utf8               test2
  #10 = Utf8               <init>
  #11 = Utf8               ()V
  #12 = Utf8               Code
  #13 = Utf8               LineNumberTable
  #14 = Utf8               method
  #15 = Utf8               method2
  #16 = Utf8               main
  #17 = Utf8               ([Ljava/lang/String;)V
  #18 = Utf8               SourceFile
  #19 = Utf8               Test.java
  #20 = NameAndType        #10:#11        // "<init>":()V
  #21 = Utf8               Test
  #22 = NameAndType        #14:#11        // method:()V
  #23 = NameAndType        #15:#11        // method2:()V
  #24 = Utf8               java/lang/Object
{
  private int test;
    descriptor: I
    flags: (0x0002) ACC_PRIVATE

  private static int test2;
    descriptor: I
    flags: (0x000a) ACC_PRIVATE, ACC_STATIC

  public Test();
    descriptor: ()V
    flags: (0x0001) ACC_PUBLIC
    Code:
      stack=1, locals=1, args_size=1
         0: aload_0
         1: invokespecial #1                  // Method java/lang/Object."<init>":()V
         4: return
      LineNumberTable:
        line 1: 0

  void method();
    descriptor: ()V
    flags: (0x0000)
    Code:
      stack=0, locals=1, args_size=1
         0: return
      LineNumberTable:
        line 5: 0

  static void method2();
    descriptor: ()V
    flags: (0x0008) ACC_STATIC
    Code:
      stack=0, locals=0, args_size=0
         0: return
      LineNumberTable:
        line 6: 0

  public static void main(java.lang.String[]);
    descriptor: ([Ljava/lang/String;)V
    flags: (0x0009) ACC_PUBLIC, ACC_STATIC
    Code:
      stack=2, locals=3, args_size=1
         0: new           #2                  // class Test
         3: dup
         4: invokespecial #3                  // Method "<init>":()V
         7: astore_1
         8: new           #2                  // class Test
        11: dup
        12: invokespecial #3                  // Method "<init>":()V
        15: astore_2
        16: aload_1
        17: invokevirtual #4                  // Method method:()V
        20: aload_2
        21: invokevirtual #4                  // Method method:()V
        24: aload_1
        25: pop
        26: invokestatic  #5                  // Method method2:()V
        29: aload_2
        30: pop
        31: invokestatic  #5                  // Method method2:()V
        34: return
      LineNumberTable:
        line 9: 0
        line 10: 8
        line 12: 16
        line 13: 20
        line 15: 24
        line 16: 29
        line 17: 34
}
SourceFile: "Test.java"
```

오브젝트 코드 관련해서 읽으면서 좀 찾아본 내용들 

major version: 55   // java 1.1 부터 45 으로 나타낸다. 55는 java 11로 컴파일된 클래스 파일라는 정보를 알려준다.

Constant pool : 클래스의 코드를 동작시키기 위한 상수들을 모아놓은 것

Constant pool은 코드에서 사용된 리터럴들과 컴파일러에 의해 생성된 symbolic references들을 모두 포함한다.

symbolic references: 코드에 의해 참조되는 클래스명, 메서드명, 필드명이 포함된다. jvm은 이를 통해 각기 다른 클래스간의 link를 생성한다. 


---
바이트 코드 상에서 결국 invokevirtual   vs  invokestatic 두 가지 instruction만 다르고 상수풀을 참조하고 있는 부분은 같다. 

그렇다면 두 명령어는 무슨 차이가 있을까? 

#### invokestatic

```
invokestatic indexbyte1 indexbyte2  

indexbyte1 indexbyte2 : 호출하고자하는 클래스 함수가 현재 클래스의 상수풀에서 몇 번째 엔트리에 존재하는 지를 나타낸다. (총 2바이트이며 2^16개의 엔트리를 참조할 수 있다.)

즉 참조되는 상수풀은 (indexbyte1 << 8) | indexbyte2) 가 된다.

index에 해당하는 constant pool 엔트리는 호출하고자 하는 메서드의 symbolic reference를 제공한다

(이 symbolic refernce는 호출하고자하는 class에 대한 constant pool의 인덱스 정보와, 실제 호출하고자하는 함수명과 함수에 대한 descriptor 정보를 제공한다.)

이 symbolic reference에 대한  Method Resolution이 성공적으로 끝났다면 함수가 실행된다. 

(이 때 만약 실행하고자하는 메서드가 존재하는 class가 아직 initialize 되지 않았다면, 해당 클래스는 jvm에 의해 initialize 된다.)

(함수 실행 시  operand stack에는 resolve된 함수에 descriptor에 정의된대로 argument로 정확하게 들어와있어야 정상 실행이 되게 된다.)

```
---
#### invokevirtual
```
invokestatic indexbyte1 indexbyte2  

indexbyte1 indexbyte2 : 호출하고자하는 클래스 함수가 현재 클래스의 상수풀에서 몇 번째 엔트리에 존재하는 지를 나타낸다. (총 2바이트이며 2^16개의 엔트리를 참조할 수 있다.)

즉 참조되는 상수풀은 (indexbyte1 << 8) | indexbyte2) 가 된다.

index에 해당하는 constant pool 엔트리는 호출하고자 하는 메서드의 symbolic reference를 제공한다

(이 symbolic refernce는 호출하고자하는 class에 대한 constant pool의 인덱스 정보와, 실제 호출하고자하는 함수명과 함수에 대한 descriptor 정보를 제공한다.)

이 symbolic reference에 대한  Method Resolution이 성공적으로 끝났다면 함수가 실행된다. 

(이 때 만약 실행하고자하는 메서드가 존재하는 class가 아직 initialize 되지 않았다면, 해당 클래스는 jvm에 의해 initialize 된다.)

(함수 실행 시  operand stack에는 resolve된 함수에 descriptor에 정의된대로 argument로 정확하게 들어와있어야 정상 실행이 되게 된다.)

이 후 함수가 signature polymorphic 인지 여부에 따라 함수 실행 과정이 조금 바뀌게 된다. 

(signature polymorphic에 대한 부분은 아직 이해 하지 못했음.. 차후 막히거나 해당 부분의 에러 겪게 되면 다시 찾아보자)


-  호출한 함수가 signature polymorphic 가 아닌 경우 해당 메서드를 호출한 객체에서 look up 과정을 거친다.

1. 해당 메서드를 호출한 object ref에서 실제 호출하고자하는 resolve된 메소드가 있다면 해당 함수를 실행하고 look up 과정을 끝낸다.

2. 1번 과정에서 메서드를 찾지 못했고, 만약 object ref가 슈퍼클래스를 가지고 있다면 슈퍼클래스에 대해서 1번의 과정을 반복한다.

3. 만약 1, 2의 과정에서 호출하고자자 하는 메서드를 발견하지 못했다면 AbstractMethodError가 발생한다.

(또한 이 과정에서 object ref도 코드의 정의된 대로 유효한 object ref여야 한다.)

- 호출한 함수가 signature polymorphic 인 경우 
If the named method is invokeExact, the instance of java.lang.invoke.MethodType must be semantically equal to the type descriptor of the receiving method handle objectref. The method handle to be invoked is objectref.

If the named method is invoke, and the instance of java.lang.invoke.MethodType is semantically equal to the type descriptor of the receiving method handle objectref, then the method handle to be invoked is objectref.

If the named method is invoke, and the instance of java.lang.invoke.MethodType is not semantically equal to the type descriptor of the receiving method handle objectref, then the Java Virtual Machine attempts to adjust the type descriptor of the receiving method handle, as if by a call to java.lang.invoke.MethodHandle.asType, to obtain an exactly invokable method handle m. The method handle to be invoked is m.

```
참고 : [Jvm_Instructions](https://docs.oracle.com/javase/specs/jvms/se7/html/jvms-6.html#jvms-6.5.invokevirtual)

---
### javap 사용 방법

**javap : 하나 이상의 class 파일을 역어셈블한다.**

여러 옵션들 

 -v  -verbose : Print additional information (여러 추가적인 정보들을 출력한다)
 
 -s : Print internal type signatures
 
 ---
 클래스 멤버 또는 메서드에 대한 접근 제어자에 따른 옵션 
 
 ```
 -private : Show all classes and members  (-p와 -private은 동일하다)
 -public : Show only public classes and members
 -protected :  Show protected/public classes and members
 -package :   Show package/protected/public classes and members (default)
 ```

javap -v -p -s 클래스명.class > 원하는파일명.txt

를 통해 역어셈블된 자바 바이트 코드를 확인해서 분석할 수 있다. 

---
### signature polymorphic

a signature polymorphic method is one which can operate with any of a wide range of call signatures and return types.

```
다음 조건을 모두 만족해야 signature polymorphic를 만족한다.

It is declared in the java.lang.invoke.MethodHandle class. // java.lang.invoke.MethodHandle class.에 선언된 메서드 인 경우 

It has a single formal parameter of type Object[]. // 오브젝트 배열 형태의 단일 파라미터가 존재하는 경우 

It has a return type of Object. //리턴 타입이 object인 경우 

It has the ACC_VARARGS and ACC_NATIVE flags set. // 해당 두가지 플래그가 설정된 경우 ..
```
>> 일반적인 함수 호출과 구별되야될 필요성이 있는 것 같기는한데, 내용 읽어봐도 구체적으로 뭘 의미하는지 잘 모르겠음..  차후 내용에서 막히는 거 생기거나 밑에 레벨 공부할 일 생기면 다시 보자..
 
 
---
### 결론

https://tourspace.tistory.com/12 와 https://docs.oracle.com/javase/specs/jvms/se7/html/jvms-6.html#jvms-6.5.invokevirtual 를 참고해보았을 때 

함수 호출 과정에서 jvm instruction에서 함수를 호출한 object가 유효한지, 해당 object 또는 object의 super class에 메서드가 존재하는지 여부를 체크하는 과정이 

invokevirtual의 경우 추가적으로 일어난다. 

그러나 실제 함수의 성능에 있어서 static인지 non- static인지 여부는 critical 하지 않으며, 속도 차이도 거의 나지 않는다.

자바의 정석 책에서도 그렇고,  https://stackoverflow.com/questions/3805155/are-java-static-calls-more-or-less-expensive-than-non-static-calls

해당 링크에서 또한 단순 실행 속도 향상의 목적 여부로 static, non-static을 가르지 말라고 하니 목적에 맞게 알맞게 사용하는 것이 좋겠다.

---
signature polymorphic가 어떤 것인지, 실제 jvm 구현체에서 symbol resolution이 어떻게 일어나는지 자료를 찾기도 어렵고, 읽어봐도 잘 이해한되는 부분들이 많아

차후 자료들 찾으면 해당 부분도 채워놓자. 

---
1. 일반적으로 자바에서 대다수의 함수는 가상함수 개념이 들어가며, vtable을 활용하여 실제 메모리상에 바인딩된 위치를 찾게 된다. 

2. 자바에서 다형성을 활용하기 위해 인터페이스로 특정 인스턴스를 참조하고, 해당 인터페이스로 함수를 호출하는 경우 invokeinterface로 함수를 호출한다.

3. 자바에서 static 함수들을 호출하는 경우 invokestatic으로 동작하며, 생성자등의 특수한 function들은 invokespecial로 호출한다. 

이렇게 단순 함수를 호출하는데 사용하는 jvm instruction만 해도 4개가 된다. 이중에서 다형성과 관련된 내용을 살펴보면, 

자바에서 객체의 헤더인 mark와 klass중, klass는 해당 클래스에 대한 메타데이터를 가지고 있는 klass oop 객체를 포인팅한다. 

klass oop는 객체에 대한 많은 메타 정보를 가지고 있다.

- vtable에는 객체에서 호출할 수 있는 가상메서드가 실제 메모리에 어디에 바인딩 되어있는지에 대한 정보를 가지고 있다.
  이 때 해당 테이블에는 상위 객체로부터 상속받은 메서드들도 존재한다. 그러나, 특정 함수에 대해서 하위 클래스에서 override 하는 경우, 
  기존 상위 객체의 method를 포인팅하던 vtable에 동일한 offeset에 override한 메서드의 메모리 주소를 담게된다.
  (즉, 상위 클래스로 인스턴스를 참조해 메서드를 호출했을 때, 오버라이드 된 메서드가 호출되는 이유는, 더 이상 상위 클래스의 메서드가 아닌 override된 메서드를 포인팅하기 때문이다.)
  
- vtable에는 meta 데이터로 itable에 대한 정보도 가지고 있다.
- 만일 특정 객체가 인터페이스를 구현하고 있고, 인터페이스로 해당 인스턴스를 참조한 상태에서 함수를 호출하는 경우, 해당 인스턴스의 vtable -> itable을 통해 실제 객체가 구현하고 있는
- 메서드에 대한 정보를 찾아서 함수를 호출하게 된다. 


---
### REFERENCE 
[REF 1](https://iamsang.com/blog/2012/08/19/introduction-to-java-bytecode/)

[REF 2](https://tlo-developer.tistory.com/262)

[REF 3](https://wonit.tistory.com/589)

[REF 4](https://stackoverflow.com/questions/10209952/what-is-the-purpose-of-the-java-constant-pool)


[Naver D2: JVM Internal](https://d2.naver.com/helloworld/1230)

https://tourspace.tistory.com/12

https://github.com/HomoEfficio/dev-tips/blob/master/Back%20to%20the%20Essence%20-%20Java%20%EC%BB%B4%ED%8C%8C%EC%9D%BC%EC%97%90%EC%84%9C%20%EC%8B%A4%ED%96%89%EA%B9%8C%EC%A7%80%20-%20(1).md

https://github.com/HomoEfficio/dev-tips/blob/master/Back%20to%20the%20Essence%20-%20Java%20%EC%BB%B4%ED%8C%8C%EC%9D%BC%EC%97%90%EC%84%9C%20%EC%8B%A4%ED%96%89%EA%B9%8C%EC%A7%80%20-%20(2).md

https://blogs.oracle.com/javamagazine/post/mastering-the-mechanics-of-java-method-invocation

https://velog.io/@dev_dong07/Java-%EA%B0%9D%EC%B2%B4%EB%8A%94-%EC%96%B4%EB%96%BB%EA%B2%8C-%EC%9D%B4%EB%A3%A8%EC%96%B4%EC%A0%B8-%EC%9E%88%EC%9D%84%EA%B9%8C

https://lukasatkinson.de/2018/interface-dispatch/
